branflake/__init__.py
branflake-0.0.0.dev5.dist-info/LICENSE
branflake-0.0.0.dev5.dist-info/METADATA
branflake-0.0.0.dev5.dist-info/WHEEL
branflake-0.0.0.dev5.dist-info/top_level.txt
branflake-0.0.0.dev5.dist-info/RECORD
