Metadata-Version: 2.1
Name: branflake
Version: 0.0.0.dev5
Summary: A modified, simplified 128-bit pseudo-flake ID generator for Python.
Author-email: Curt Gilman <curt@gilm.net>
License: MIT
Project-URL: Homepage, https://github.com/curt/branflake
Project-URL: Bug Tracker, https://github.com/curt/branflake/issues
Keywords: flake,flakeid
Classifier: Development Status :: 2 - Pre-Alpha
Classifier: Programming Language :: Python :: 3
Classifier: License :: OSI Approved :: MIT License
Classifier: Operating System :: OS Independent
Requires-Python: >=3.6
License-File: LICENSE
